django_auth_jwks/__init__.py
django_auth_jwks/apps.py
django_auth_jwks/authentication.py
django_auth_jwks/decorators.py
django_auth_jwks/middleware.py
django_auth_jwks/settings.py
django_auth_jwks/verifier.py
django_auth_jwks-1.0.1.dist-info/licenses/LICENSE
django_auth_jwks-1.0.1.dist-info/METADATA
django_auth_jwks-1.0.1.dist-info/WHEEL
django_auth_jwks-1.0.1.dist-info/top_level.txt
django_auth_jwks-1.0.1.dist-info/RECORD
