Metadata-Version: 2.4
Name: django-auth-jwks
Version: 1.0.1
Summary: Reusable Django library for JWT verification using JWKS with caching
Author: Ankit
License-Expression: MIT
Keywords: django,jwt,jwks,authentication,rest-framework
Classifier: Development Status :: 4 - Beta
Classifier: Framework :: Django
Classifier: Framework :: Django :: 3.2
Classifier: Framework :: Django :: 4.0
Classifier: Framework :: Django :: 4.1
Classifier: Framework :: Django :: 4.2
Classifier: Intended Audience :: Developers
Classifier: Programming Language :: Python
Classifier: Programming Language :: Python :: 3
Classifier: Programming Language :: Python :: 3.8
Classifier: Programming Language :: Python :: 3.9
Classifier: Programming Language :: Python :: 3.10
Classifier: Programming Language :: Python :: 3.11
Classifier: Topic :: Software Development :: Libraries :: Python Modules
Requires-Python: >=3.8
License-File: LICENSE
Requires-Dist: django>=3.2
Requires-Dist: djangorestframework==3.16.1
Requires-Dist: cryptography==45.0.6
Requires-Dist: PyJWT==2.10.1
Dynamic: license-file
